{
  "document_id": "Buda_(City_of),_TX_Combination_Tax_&_Ltd_Revenue_COO,_Srs_2026__2026-03-03__Final__101332",
  "issue": "Buda (City of), TX Combination Tax & Ltd Revenue COO, Srs 2026",
  "issue_slug": "Buda_(City_of),_TX_Combination_Tax_&_Ltd_Revenue_COO,_Srs_2026",
  "doc_type": "Final",
  "pdf_url": "https://www.i-dealprospectus.com/api/PdfDownload/101332?action=Get",
  "parsed_at": "2026-03-29T07:18:48.012311+00:00",
  "page_count_examined": 12,
  "extracted": {
    "issuer": "Buda (City of), TX Combination Tax & Ltd Revenue COO, Srs 2026",
    "offering_type": "official_statement",
    "sale_type": "Comp",
    "par_amount_from_manifest": 27210000.0,
    "par_amount_from_text": "27,210,000",
    "tax_status": "taxable",
    "dated_date": "March 26, 2026",
    "delivery_date": null,
    "call_features": [
      "optional_redemption"
    ],
    "underwriter": "Specialized Public Finance Inc. (FA)",
    "financial_advisor": null
  },
  "source_excerpt": "[PAGE 1]\n \n \nOFFICIAL STATEMENT \n \n Dated March 3, 2026  Rating: \n S&P:  \u201cAA\u201d \n (See \u201cOTHER INFORMATION \u2013   \nNEW ISSUE \u2013 BOOK-ENTRY-ONLY R ATING\u201d herein) \n \nIn the opinion of McCall, Parkhurst & Horton L.L.P., Bond Counsel, interest on the Certificates, defined below, will be excludable \nfrom gross income for federal income ta x purposes under statutes, regul ations, published rulings and court decisions existing o n \nthe date thereof, subject to the matters described under \u201cTAX MATTERS\u201d herein, including the alternative minimum tax on certain \ncorporations. \n \n$27,210,000 \nCITY OF BUDA, TEXAS \n(A political subdivision of the State of Texas located in Hays County) \nCOMBINATION TAX AND LIMITED REVENUE CERTIFICATES OF OBLIGATION, SERIES 2026 \n \nDated Date: March 26, 2026  Due: Au gust 15, as shown on page 2 \nInterest accrues from the Date of Initial Delivery (defined below) \n \nPAYMENT TERMS . . . Interest on the $27,210,000 City of Buda, Texas, Combination Tax and Limited Revenue Certificates of \nObligation, Series 2026 (the \u201cCertificates\u201d) will accrue from the Date of Initial Delivery, defined below, and will be payable \nFebruary 15 and August 15 of each year commencing February 15, 2027, until maturity or earlier redemption, and will be calculated \non the basis of a 360-day year consisting of twelve 30-day months.  The definitive Certificates will be initially registered an d \ndelivered only to Cede & Co., the nom inee of The Depository Trust Company, New York, New York (\u201cDTC\u201d) pursuant to the \nbook-entry-only system described herein.  Beneficial ownership of the Certificates may be acquired in denominations of $5,000 or \nintegral multiples thereof.  No physical delivery of the Certificates will be made to the beneficial owners thereof.  Principal of, \npremium, if any, and interest on the Certifi cates will be payable by the Paying Agent/Registrar to Cede & Co., which will make \ndistribution of the amounts so paid to the participating members of DTC for subsequent payment to the beneficial owners of the \nCertificates.  See \u201cTHE CERTIFICATES \u2013 BOOK-ENTRY-ONLY SYSTEM\u201d herein.  The initial Paying Agent/Registrar is The Bank \nof New York Mellon Trust Company, National Associat ion, Houston, Texas (s ee \u201cTHE CERTIFICATES \u2013  PAYING \nAGENT/REGISTRAR\u201d). \n \nAUTHORITY FOR ISSUANCE . . . The Certificates are issued pursuant to the Constitution and general laws of the State of Texas (the \n\u201cState\u201d), particularly Subchapter C of Chapter 271, Texas Local Government Code, as amended, and Chapter 1502, Texas \nGovernment Code, as amended, and an ordinanc e (the \u201cCertificate Ordinance\u201d) adopted by  the City Council of the City of Buda, \nTexas (the \u201cCity\u201d) on March 3, 2026.  The Certificates constitu te direct obligations of the City, payable from a combination of  (i) \nthe levy and collection of a continuing, dire ct annual ad valorem tax, within the lim its prescribed by law, on all taxable prop erty \nwithin the City, and (ii) a limited pledge of surplus net revenues  of the City\u2019s combined waterworks and sewer system, not to \nexceed $1,000 as provided in the Certificat e Ordinance (see \u201cTHE  CERTIFICATES \u2013 A UTHORITY FOR ISSUANCE\u201d and \u201cTHE \nCERTIFICATES \u2013 SECURITY AND SOURCE OF PAYMENT\u201d). \n \nPURPOSE . . . Proceeds from the sale of the Certificates will be used for the purpose of paying contractual obligations incurred or \nto be incurred by the City for (1) constructing, improving and/or extending the City's waterworks and sewer system, including the \nOld Black Colony water storage facilities, re use water system expansion, water and wastewater lines, wastewater treatment plant  \nimprovements and wastewater interceptor expansion, including the acquisition of any necessary easements or land; (2) constructing, \nimproving, renovating, expanding and/or equipping City parks an d related costs for improvements to the City\u2019s Sportsplex and \nCity Park; and (3) paying relate d professional services including for construction man agers, engineers, archit",
  "pages": [
    {
      "page_number": 1,
      "text": " \n \nOFFICIAL STATEMENT \n \n Dated March 3, 2026  Rating: \n S&P:  \u201cAA\u201d \n (See \u201cOTHER INFORMATION \u2013   \nNEW ISSUE \u2013 BOOK-ENTRY-ONLY R ATING\u201d herein) \n \nIn the opinion of McCall, Parkhurst & Horton L.L.P., Bond Counsel, interest on the Certificates, defined below, will be excludable \nfrom gross income for federal income ta x purposes under statutes, regul ations, published rulings and court decisions existing o n \nthe date thereof, subject to the matters described under \u201cTAX MATTERS\u201d herein, including the alternative minimum tax on certain \ncorporations. \n \n$27,210,000 \nCITY OF BUDA, TEXAS \n(A political subdivision of the State of Texas located in Hays County) \nCOMBINATION TAX AND LIMITED REVENUE CERTIFICATES OF OBLIGATION, SERIES 2026 \n \nDated Date: March 26, 2026  Due: Au gust 15, as shown on page 2 \nInterest accrues from the Date of Initial Delivery (defined below) \n \nPAYMENT TERMS . . . Interest on the $27,210,000 City of Buda, Texas, Combination Tax and Limited Revenue Certificates of \nObligation, Series 2026 (the \u201cCertificates\u201d) will accrue from the Date of Initial Delivery, defined below, and will be payable \nFebruary 15 and August 15 of each year commencing February 15, 2027, until maturity or earlier redemption, and will be calculated \non the basis of a 360-day year consisting of twelve 30-day months.  The definitive Certificates will be initially registered an d \ndelivered only to Cede & Co., the nom inee of The Depository Trust Company, New York, New York (\u201cDTC\u201d) pursuant to the \nbook-entry-only system described herein.  Beneficial ownership of the Certificates may be acquired in denominations of $5,000 or \nintegral multiples thereof.  No physical delivery of the Certificates will be made to the beneficial owners thereof.  Principal of, \npremium, if any, and interest on the Certifi cates will be payable by the Paying Agent/Registrar to Cede & Co., which will make \ndistribution of the amounts so paid to the participating members of DTC for subsequent payment to the beneficial owners of the \nCertificates.  See \u201cTHE CERTIFICATES \u2013 BOOK-ENTRY-ONLY SYSTEM\u201d herein.  The initial Paying Agent/Registrar is The Bank \nof New York Mellon Trust Company, National Associat ion, Houston, Texas (s ee \u201cTHE CERTIFICATES \u2013  PAYING \nAGENT/REGISTRAR\u201d). \n \nAUTHORITY FOR ISSUANCE . . . The Certificates are issued pursuant to the Constitution and general laws of the State of Texas (the \n\u201cState\u201d), particularly Subchapter C of Chapter 271, Texas Local Government Code, as amended, and Chapter 1502, Texas \nGovernment Code, as amended, and an ordinanc e (the \u201cCertificate Ordinance\u201d) adopted by  the City Council of the City of Buda, \nTexas (the \u201cCity\u201d) on March 3, 2026.  The Certificates constitu te direct obligations of the City, payable from a combination of  (i) \nthe levy and collection of a continuing, dire ct annual ad valorem tax, within the lim its prescribed by law, on all taxable prop erty \nwithin the City, and (ii) a limited pledge of surplus net revenues  of the City\u2019s combined waterworks and sewer system, not to \nexceed $1,000 as provided in the Certificat e Ordinance (see \u201cTHE  CERTIFICATES \u2013 A UTHORITY FOR ISSUANCE\u201d and \u201cTHE \nCERTIFICATES \u2013 SECURITY AND SOURCE OF PAYMENT\u201d). \n \nPURPOSE . . . Proceeds from the sale of the Certificates will be used for the purpose of paying contractual obligations incurred or \nto be incurred by the City for (1) constructing, improving and/or extending the City's waterworks and sewer system, including the \nOld Black Colony water storage facilities, re use water system expansion, water and wastewater lines, wastewater treatment plant  \nimprovements and wastewater interceptor expansion, including the acquisition of any necessary easements or land; (2) constructing, \nimproving, renovating, expanding and/or equipping City parks an d related costs for improvements to the City\u2019s Sportsplex and \nCity Park; and (3) paying relate d professional services including for construction man agers, engineers, architects, attorneys, \nauditors, financial advisors, fiscal agents and costs related to issuing the Certificates.  See \u201cTHE CERTIFICATES \u2013 PURPOSE.\u201d \n \n        \n \nCUSIP PREFIX:  118828 \nMATURITY SCHEDULE, INTEREST RATES, PRICES AND OTHER TERMS \nSEE INSIDE COVER PAGE \n        \n \nLEGALITY . . . The Certificates are offered for delivery when, as and if  issued and received by the Purchaser and subject to the \napproving opinion of the Attorney General of the State of Texas and the opinion of McCall, Park hurst & Horton L.L.P., Austin, \nTexas, Bond Counsel (see \u201cAPPENDIX C \u2013 FORM OF BOND COUNSEL\u2019S OPINION\u201d). \n \nDELIVERY . . . It is expected that the Certificates will be available for delivery through DTC on March 26, 2026 (the \u201cDate of Initial \nDelivery\u201d). "
    },
    {
      "page_number": 2,
      "text": " 2 \nMATURITY SCHEDULE \n \n \n8/15 Principal Interest Initial CUSIP\nMaturity Amount Rate Yield Numbers\n(1)\n2028 630,000$    5.000% 2.200% 118828PD8\n2029 665,000      5.000% 2.240% 118828PE6\n2030 695,000      5.000% 2.280% 118828PF3\n2031 730,000      4.000% 2.340% 118828PG1\n2032 760,000      5.000% 2.450% 118828PH9\n2033 800,000      5.000% 2.500% 118828PJ5\n2034 840,000      5.000% 2.590% 118828PK2\n2035 880,000      5.000% 2.710% 118828PL0\n2036 925,000      5.000% 2.810%\n(2)\n118828PM8\n2037 975,000      5.000% 2.910%\n(2)\n118828PN6\n2038 1,020,000   5.000% 3.080%\n(2)\n118828PP1\n2039 1,070,000   5.000% 3.230%\n(2)\n118828PQ9\n2040 1,120,000   5.000% 3.270%\n(2)\n118828PR7\n2041 1,180,000   5.000% 3.370%\n(2)\n118828PS5\n2042 1,235,000   4.000% 3.850%\n(2)\n118828PT3\n2043 1,290,000   4.000% 3.950%\n(2)\n118828PU0\n2044 1,340,000   4.000% 4.050% 118828PV8\n2045 1,390,000   4.000% 4.120% 118828PW6\n2046 1,450,000   4.125% 4.200% 118828PX4\n2047 1,505,000   4.250% 4.270% 118828PY2\n2048 1,575,000   4.250% 4.330% 118828PZ9\n2049 1,640,000   4.250% 4.370% 118828QA3\n2050 1,710,000   4.375% 4.410% 118828QB1\n2051 1,785,000   4.375% 4.440% 118828QC9  \n \n(Interest Accrues from the Date of Initial Delivery) \n_____________ \n(1) CUSIP \u00ae is a registered trademark of the American Bankers Association.  CUSIP Global Services (\u201cCGS\u201d) is managed on \nbehalf of the American Bankers Association by FactSet Research Systems Inc. Copyright(c) CUSIP Global Services.  All rights \nreserved.  CUSIP\u00ae data herein is provided by CUSIP Global Services.  This data is not intended to create a database and does \nnot serve in any way as a substitute for the CGS database.  CUSIP\u00ae numbers are provided for convenience of reference only.  \nThe CUSIP number for a specific maturity is subject to being ch anged after the initial issuance of obligations due to various \nsubsequent actions including, but not limited to, a refunding in whole or in pa rt, procurement of secondary market portfolio \ninsurance or other similar enhancement by investors that is applicable to all or a portion of certain maturities of obligations .  \nNone of the City, the Financial Advisor, the Purchaser or their agents or couns el assume responsibility for the accuracy of \nsuch numbers. \n(2) Yield calculated based on the assumption that the Certificates denoted and sold at a premium will be redeemed on August 15, \n2035, the first optional redemption date for such Certificates, at a redemption pric e of par plus accrued interest to the \nredemption date. \n \n \nOPTIONAL REDEMPTION . . . The City reserves the right, at its option, to redeem Certificates having stated maturities on and after \nAugust 15, 2036, in whole or from time to time in part, in principal amounts of $5,000 or any integral multiple thereof, on August \n15, 2035, or any date thereafter, at the par value thereof plus accrued interest to the date of redemption (see \u201cTHE CERTIFICATES \n\u2013 OPTIONAL REDEMPTION\u201d). \n \n \n \n \n \n \n(THE REMAINDER OF THIS PAGE INTENTIONALLY LEFT BLANK) \n "
    },
    {
      "page_number": 3,
      "text": " 3 \nThis Official Statement, which includes the cover page and the Ap pendices hereto, does not constitute an offer to sell or the \nsolicitation of an offer to buy in any jurisdiction to any person to whom it is unlawful to make such offer, solicitation or sa le.  No \ndealer, broker, salesman or other person has been authorized by the City to give any information, or to make any representations \nother than those contained in this Official Statement, and, if given or made, such other information or representations must not be \nrelied upon as having been authorized by the City or the Financial Advisor.  This Official Statement does not constitute an offer to \nsell Certificates in any jurisdiction to any person to whom it is unlawful to make such an offer in such jurisdiction. \n \nThe information set forth herein has been obtained from the City and other sources believed to be reliable, but such information is \nnot guaranteed as to accuracy or completeness and is not to be construed as the promise or guarantee of the Financial Advisor or \nthe Purchaser of the Certificates.  This Official Statement contains, in part, estimates and matters of opinion which are not intended \nas statements of fact, and no re presentation is made as to the correctness of such estimates and opinions , or that they will be  \nrealized. \n \nThe information and expressions of opinion contained herein are subject to change without notice, and neither the delivery of this \nOfficial Statement nor any sale made here under shall, under any circumstances, create any implication that there has been no \nchange in the affairs of the City or other matters described. \n \nTHE CERTIFICATES ARE EXEMPT FRO M REGISTRATION WITH THE SEC AND,  CONSEQUENTLY, HAVE NOT BEEN \nREGISTERED THEREWITH.  THE REGISTRATION, QUALIFI CATION, OR EXEMPTION OF THE CERTIFICATES IN \nACCORDANCE WITH APPLICABLE SECURITIES LAW PRO VISIONS OF THE JURISDICTION IN WHICH THE \nCERTIFICATES HAVE BEEN REGI STERED, OR EXEMPTED, SHOULD NOT BE  REGARDED AS A RECOMMENDATION \nTHEREOF.  \n \nNONE OF THE CITY, THE FINANCIAL ADVISOR, OR THE PURCHASER OF THE CERTIFICATES MAKE ANY \nREPRESENTATION OR WARRANTY WITH RESPECT TO THE INFORMATION CONTAINED IN THIS OFFICIAL STATEMENT \nREGARDING THE DEPOSITORY TRUST COMPANY OR ITS BOOK-ENTRY-ONLY SYSTEM. \n \nTABLE OF CONTENTS \n \nCITY OFFICIALS, STAFF AND CONSULTANTS ...  4 \n E LECTED OFFICIALS ...................................................  4 \n S ELECTED ADMINISTRATIVE STAFF ............................  4 \n C ONSULTANTS AND ADVISORS ...................................  4 \nOFFICIAL STATEMENT SUMMARY .......................  5 \nINTRODUCTION ..........................................................  7 \nTHE CERTIFICATES ...................................................  7 \nAD VALOREM PROPERTY TAXATION .................. 14 \n T ABLE 1 \u2013 VALUATION, EXEMPTIONS AND AD VALOREM \nTAX DEBT  ......................................................... 18 \n T ABLE 2 \u2013 VALUATION AND AD VALOREM TAX DEBT \nHISTORY ............................................................ 18 \n T ABLE 3 \u2013 TAX RATE, LEVY AND COLLECTION     \nHISTORY  ........................................................... 19 \n T ABLE 4 \u2013 TEN LARGEST TAXPAYERS ........................ 19 \n T ABLE 5 \u2013 TAX ADEQUACY ........................................ 19 \nDEBT INFORMATION ................................................. 20 \n T ABLE 6 \u2013 DEBT SERVICE REQUIREMENTS .................. 20 \n T ABLE 7 \u2013 ESTIMATED OVERLAPPING DEBT ............... 21 \n T ABLE 8 \u2013 AUTHORIZED BUT UNISSUED GENERAL \nOBLIGATION DEBT ............................................. 21 \n T ABLE 9 \u2013 INTEREST AND SINKING FUND BUDGET \nPROJECTION ....................................................... 21 \nFINANCIAL INFORMATION ..................................... 22 \n T ABLE 10 \u2013 GENERAL FUND REVENUES AND \nEXPENDITURE HISTORY ...................................... 22 \n T ABLE 11 \u2013 MUNICIPAL SALES TAX HISTORY ............. 23 \nINVESTMENTS ............................................................. 23 \n T ABLE 12 \u2013 CURRENT INVESTMENTS .......................... 25 \nTAX MATTERS ............................................................. 25 \nCONTINUING DISCLOSURE OF INFORMATION 27 \nLEGAL MATTERS ....................................................... 29 \nOTHER INFORMATION ............................................. 29 \n \nAPPENDICES \nGENERAL INFORMATION REGARDING THE CITY  A \nEXCERPTS FROM THE ANNUAL FINANCIAL \nREPORT ..................................................................  B \nFORM OF BOND COUNSEL\u2019S OPINION ....................  C \n \nThe cover and inside cover pa ges hereof, this page, the \nappendices included herein and any addenda, supplement or \namendment hereto, are part of the Official Statement. \n "
    },
    {
      "page_number": 4,
      "text": " 4 \nCITY OFFICIALS, STAFF AND CONSULTANTS \n \nELECTED OFFICIALS \n \n \nCity Council \n Length of \nService \n Term \nExpires \n \nLee Urbanovsky \nMayor \n \n 6 Years  November 2026  \nMatt Smith \nCouncilmember, At-Large Position 1 \n \n 5 Years  November 2028  \nMonica Davidson \nCouncilmember, At-Large Position 2 \n \n 5 Years  November 2026  \nLaVonia Horne-Williams \nCouncilmember, At-Large Position 3 \n \n 4 Years  November 2027  \nGreg Bowles \nCouncilmember, Single Member District A \n \n 1\u00bd Years  November 2027  \nEvan Ture \nCouncilmember, Single Member District B \n \n 8 Years  November 2026  \nKimberly Goodman \nCouncilmember, Single Member District C \n \n 0 Years  November 2028  \n \n \nS\nELECTED ADMINISTRATIVE STAFF \n \nName \n  \nPosition \n \nMicah Grau  City Manage r  \nBianca Redmon  Finance Directo r  \nAngela Verduzco  Assi stant Finance Director  \nAlicia Ramirez  Cit y Clerk  \n \n \nCONSULTANTS AND ADVISORS \n \nAuditors ...................................................................................................................... ............................ Weaver and Tidwell, L.L.P. \nCertified Public Accountants \n Austin, Texas \n \nBond Counsel .................................................................................................................. ........... McCall, Parkhurst & Horton L.L.P. \n Austin, Texas \n \nFinancial Advisor ............................................................................................................................... Specialized Public Finance Inc. \n Austin, Texas \n \nFor additional information regarding the City, please contact: \n \nMicah Grau Jennifer Ritte r\nCity Manager Managing Director\nCity of Buda o r Specialized Public Finance Inc.\n405 East Loop Street 248 Addie Roy Road\nBuilding 100 Suite B-103\nBuda, Texas  78610 Austin, Texas  78746\n(512) 523-1017 (512) 275-7300   "
    },
    {
      "page_number": 5,
      "text": " 5 \nOFFICIAL STATEMENT SUMMARY \nThis summary is subject in all respects to the more complete information and definitions contained or incorporated in this Official \nStatement.  The offering of the Certificates to potential investors is made only by means of this entire Official Statement.  N o \nperson is authorized to detach this summary from this Official Statement or to otherwise use it without the entire Official Statement. \n \n \nTHE CITY ........................................  The City of Buda, Texas (the \u201cCity\u201d) is a political subdivision located in Hays Coun ty, and \noperating as a home-rule city under the laws of the State of Texas and a charter approved by \nthe City\u2019s voters in 2007.  Th e City is approximately 2.41 square miles in area (see \n\u201cAPPENDIX A \u2013 GENERAL INFORMATION REGARDING THE CITY\u201d). \n \nTHE CERTIFICATES ........................  The $27,210,000 Combination Tax and Limited Revenue Certificates of Obligation, Series \n2026 (the \u201cCertificates\u201d) are issued as serial Certificates maturing on August 15 in the years \n2028 through and including 2051 (see \u201cTHE CERTIFICATES \u2013 GENERAL\u201d). \n \nPAYMENT OF INTEREST ..................  Interest on the Certificates  will accrue from the Date of Initial Delivery and is payable \nFebruary 15, 2027, and each August 15 and February 15 thereafter until maturity or prior \nredemption (see \u201cTHE CERTIFICATES \u2013 G ENERAL\u201d and \u201cTHE CERTIFICATES \u2013 \nOPTIONAL REDEMPTION\u201d). \n \nAUTHORITY FOR ISSUANCE ............  The Certificates are issued pursuant to the general laws of the State, particularly Subchapter \nC of Chapter 271, Texas Local Government  Code, as amended, Chapter 1502, Texas \nGovernment Code, as amended, and an ordinance adopted by the City Council of the City on \nMarch 3, 2026 authorizing the issuance of the Certificates (the \u201cCertificate Ordinance\u201d).  See \n\u201cTHE CERTIFICATES \u2013 AUTHORITY FOR ISSUANCE.\u201d \n \nSECURITY FOR THE CERTIFICATES .  The Certificates constitute direct obligations  of the City, payable from a continuing, direct \nannual ad valorem tax levied on all taxable property within the City, within the limits \nprescribed by law, as provided in the Certific ate Ordinance and a limited pledge of surplus \nnet revenues of the City\u2019s combined waterworks and sewer system not to exceed $1,000 (see \n\u201cTHE CERTIFICATES \u2013 SECURITY AND SOURCE OF PAYMENT\u201d). \n \nREDEMPTION ..................................  The City reserves the right, at its option, to redeem Certificates having stated maturitie s on \nand after August 15, 2036, in whole or from time to time in part, in principal amounts of \n$5,000 or any integral multiple thereof, on August 15, 2035, or any date thereafter, at the par \nvalue thereof plus accrued interest to the date of redemption (see \u201cTHE CERTIFICATES \u2013 \nOPTIONAL REDEMPTION\u201d). \n \nTAX EXEMPTION .............................  In the opinion of Bond Counsel, the interest on the Certificates will be excludable from gross \nincome for federal income tax purposes under statutes, regulations, published rulings and \ncourt decisions existing on the date thereof, subject to the matters described under the caption \n\u201cTAX MATTERS\u201d herein, including the alternative minimum tax on certain corporations. \n \nUSE OF PROCEEDS ..........................  Proceeds from the sale of th e Certificates will be used for the purpose of paying contractual \nobligations incurred or to be incurred by the City for (1) constructing, improving and/or \nextending the City's waterworks and sewer system, including the Old Black Colony water \nstorage facilities, reuse water system expansion, water and wastewater lines, wastewater \ntreatment plant improvements and wastewat er interceptor expansion, including the \nacquisition of any necessary easements or land; (2) constructing, improving, renovating, \nexpanding and/or equipping City parks and re lated costs for improvements to the City\u2019s \nSportsplex and City Park; and (3) paying re lated professional services including for \nconstruction managers, engineers,  architects, attorneys, auditors, financial advisors, fiscal \nagents and costs related to issuing the Certificates.  See \u201cTHE CERTIFICATES \u2013 PURPOSE.\u201d \n \nRATING ...........................................  The Certificates and the outstanding debt of the City have been rated \u201cAA\u201d by S&P  Global \nRatings (\u201cS&P\u201d) without regard to credit  enhancement (see \u201cOTHER INFORMATION \u2013  \nRATING\u201d). \n \nBOOK-ENTRY-ONLY SYSTEM .........  The definitive Certificates will be initially registered and delivered only to Cede & Co., the \nnominee of DTC pursuant to the book-entry-only  system described he rein.  Beneficial \nownership of the Certificates may be acquired in denominations of $5,000 or integral \nmultiples thereof.  No physical delivery of the Certificates will be made to the beneficial \nowners thereof.  Principal of, premium, if any, and interest on the Certificates will be payable \nby the Paying Agent/Registrar to Cede & Co., which will make distribution of the amounts "
    },
    {
      "page_number": 6,
      "text": " 6 \nso paid to the participating members of DTC for subsequent payment to the beneficial owners \nof the Certificates (see \u201cTHE CERTIFICATES \u2013 BOOK-ENTRY-ONLY SYSTEM\u201d). \n \nPAYMENT RECORD .........................  The City has never defaul ted on payment of its debt. \n \n \nSELECTED FINANCIAL INFORMATION \n \nFiscal Per Capita Per Capita Ratio\nYear Estimated Taxable Taxable Funded Funded Funded Debt to % of\nEnded City Assessed Assessed Tax Tax Taxable Total Tax\n9/30 Population\n(1)\nValuation Valuation Debt\n(2)\nDebt Assessed Valuation Collections\n2022 16,086 2,131,563,681$      132,510 $     93,630,000 $       5,821 $        4.39% 100.15%\n2023 16,086 2,664,187,840        165,622        91,410,000         5,683           3.43% 99.62%\n2024 16,030 2,935,872,236        183,149        89,135,000         5,561           3.04% 99.25%\n2025 16,090 3,145,828,541        195,515        101,135,000       6,286           3.21% 99.47%\n(4)\n2026 16,090 3,113,945,309        193,533        108,750,000       \n(3)\n6,759          3.49% 18.44%\n(5)\n________________ \n(1) Source:  The Municipal Advisory Council and the City. \n(2) Excludes the debt considered self-supporting.  See \u201cTable 1 \u2013 VALUATION, EXEMPTIONS AND AD VALOREM TAX DEBT.\u201d \n(3) Projected; includes the Certificates. \n(4) Unaudited collections as of September 30, 2025. \n(5) Partial collections as  of December 31, 2025. \n \n \n \n \n \n \n \n \n \n \n \n \n \n \n \n \n \n \n(THE REMAINDER OF THIS PAGE INTENTIONALLY LEFT BLANK)  "
    },
    {
      "page_number": 7,
      "text": " 7 \nOFFICIAL STATEMENT \n \nRELATING TO \n \n$27,210,000 \nCITY OF BUDA, TEXAS \nCOMBINATION TAX AND LIMITED REVENUE \nCERTIFICATES OF OBLIGATION, SERIES 2026 \n \n \nINTRODUCTION \n \nThis Official Statement, which includes the Appendices hereto , provides certain information regarding the issuance of the \n$27,210,000 City of Buda, Texas Combination Tax and Limited Revenue Certificates of Ob ligation, Series 2026 (the \n\u201cCertificates\u201d).  Capitalized terms used in this Official Statement have the same meanings assigned to such terms in the ordinance \n(the \u201cOrdinance\u201d or \u201cCertificate Ordinance\u201d), except as otherwise indicated herein. \n \nThere follows in this Official Statement descriptions of the Certificates and certain information regarding the City and its finances.  \nAll descriptions of documents contained herein are only summaries and are qualified in their entirety by reference to each such  \ndocument.  Copies of such documents may be obtained from the City\u2019s Financial Advisor, Specialized Public Finance Inc., Austin, \nTexas, by electronic mail or upon payment of reasonable copying, handling, and delivery charges. \n \nThis Official Statement speaks only as to its date, and the info rmation contained herein is subject to change.  A copy of the F inal \nOfficial Statement pertaining to the Certificates will be subm itted to the Municipal Securities Rulemaking Board through its \nElectronic Municipal Market Access (\u201cEMMA\u201d) system.  Se e \u201cCONTINUING DISCLOSURE OF INFORMATION\u201d herein for \na description of the City\u2019s undertaking to provide certain information on a continuing basis. \n \nDESCRIPTION OF THE CITY . . . The City is a political subdivision and municipal corporation of the State, duly organized and \nexisting under the laws of the State, including  the City\u2019s Home Rule Charter.  The City  first adopted its Home Rule Charter in \n2007.  The City operates under the Council/Manager form of go vernment where the Mayor and six Councilmembers are elected \nfor staggered three-year terms.  The City Manager is the chief administrative officer for the City.  Some of the services that the \nCity provides are:  public safety (police a nd fire protection), highways and streets, water and sanitary sewer utilities, sanit ation \nservices, health and social services, culture-recreation, public improvements, planning and zoni ng, and general administrative \nservices.  The estimated 2026 population is 16,090.  The City c overs approximately 2.41 square miles.  For more information \nregarding the City, see \u201cAPPENDIX A \u2013 GENERAL INFORMATION REGARDING THE CITY.\u201d \n \n \nTHE CERTIFICATES \n \nG\nENERAL . . . The Certificates are dated March 26, 2026, and mature on August 15 in each of the years and in the amounts shown \non page 2 hereof.  Interest on the Certificates will be computed on the basis of a 360-day year consisting of twelve 30-day months, \nand will be payable February 15 and August 15 of each year commencing February 15, 2027 until maturity or earlier redemption, \naccruing from the Date of Initial Delivery.   \n \nThe definitive Certificates will be issued only in fully register ed form in any integral multiple of $5,000 for any one maturit y and \nwill be initially registered and delivered only to Cede & Co., the nominee of The Depository Trust Company, New York, New \nYork (\u201cDTC\u201d), pursuant to the book-entry-only system described herein (the \u201cBook-Entry-Only System\u201d).  No physical delivery \nof the Certificates will be ma de to the owners thereof.  Principal of, premium, if any, and interest on the Certificates will be \npayable by the Paying Agent/Registrar to Cede & Co., which will ma ke distribution of the amounts so paid to the participating \nmembers of DTC for subsequent payment to the beneficial owners of the Certificates.  See \u201cBOOK-ENTRY-ONLY SYSTEM\u201d herein. \n \nAUTHORITY FOR ISSUANCE . . . The Certificates are issued pursuant to the general laws of the State, particularly Subchapter C of \nChapter 271, Texas Local Government Code, as amended, Chapter 1502, Texas Government Code, as amended, and the Certificate \nOrdinance adopted by the City Council on March 3, 2026. \n \nSECURITY AND SOURCE OF PAYMENT . . . All taxable property within the City is subject to a continuing direct annual ad valorem \ntax levied, within the limits prescribed by law, on all taxable property within the City sufficient to provide for the payment of \nprincipal of and interest on the Certificates. \n \nThe Certificates constitute direct obligations of the City, paya ble from a continuing, direct annu al ad valorem tax levied on a ll \ntaxable property within the City, within the limits prescribed by law, sufficient to provide for the payment of principal of an d \ninterest on the Certificates as provided in the Certificate Ordinance, and a limited pledge of surplus net revenues of the City \u2019s \ncombined waterworks and sewer system not to exceed $1,000. \n \nTAX RATE LIMITATION . . . All taxable property within the City is subject to the assessment, levy and collection by the City of a \ncontinuing, direct annual ad valorem tax sufficient to provide for the payment of principal of and interest on all ad valorem tax debt "
    },
    {
      "page_number": 8,
      "text": " 8 \nwithin the limits prescribed by law.  Article XI, Section 5, of  the Texas Constitution limits the maximum ad valorem tax rate f or \nhome-rule cities to $2.50 per $100 taxable assessed valuation for all purposes.  Administratively, the Attorney General of Texa s \nwill permit allocation of $1.50 of the $2.50 maximum tax rate for all general obligation debt service calculated at the time of  \nissuance based on 90% tax collections. \n \nOPTIONAL REDEMPTION . . . The City reserves the right, at its option, to redeem Certificates having stated maturities on and after \nAugust 15, 2036, in whole or from time to time in part, in principal amounts of $5,000 or any integral multiple thereof, on August \n15, 2035, or any date thereafter, at the par value thereof plus ac crued interest to the date of redemption.  If less than all o f the \nCertificates are to be redeemed, the City may select the maturiti es of such Certificates to be redeemed.  If less than all the \nCertificates of any maturity are to be redeemed, the Paying Agent/Registrar (or DTC while the Certificates are in Book-Entry-Only \nform) shall determine by lot or any other customary random method such Certificates, or portions thereof, within such maturity to \nbe redeemed.  If any Certificat e (or any portion of the principal sum thereof) shall have been called for redemption and notice  of \nsuch redemption shall have been given, su ch Certificate (or the principal amount ther eof to be redeemed) shall become due and \npayable on such redemption date and interest thereon shall cease to accrue from and after the redemption date, provided funds for \nthe payment of the redemption price and accrued interest thereon are held by the Paying Agent/Registrar on the redemption date. \n \nNOTICE OF REDEMPTION . . . Not less than 30 days prior to an optional redemption date for the Certificates, the City shall cause a \nnotice of redemption to be sent by United States mail, first-class, postage prepaid, to the registered owners of the Certificates to be \nredeemed, in whole or in part, at the address of the regi stered owner appearing on the registration books of the Paying \nAgent/Registrar at the close of business on the business day next  preceding the date of maili ng such notice.  ANY NOTICE SO \nMAILED SHALL BE CONCLUSIVELY PRESUMED TO  HAVE BEEN DULY GIVEN,  WHETHER OR NOT THE \nREGISTERED OWNER RECEIVES SUCH NOTICE.  NOTICE HAVING BEEN SO GIVEN, THE CERTIFICATES CALLED \nFOR REDEMPTION SHALL BECOME DUE AND PAYABLE ON THE SPECIFIED REDEMPTION DATE, AND \nNOTWITHSTANDING THAT ANY CERTIFICATE OR PORT ION THEREOF HAS NOT BEEN SURRENDERED FOR \nPAYMENT, INTEREST ON SUCH PORTION THEREOF SHALL CEASE TO ACCRUE. \n \nThe Paying Agent/Registrar and the City, so long as a book-entry-onl y system is used for the Cert ificates will send any notice of \nredemption, notice of proposed amendment to the Ordinance or other notices with respect  to the Certificates only to DTC.  Any \nfailure by DTC to advise any DTC participant, or of any DTC participant or indirect participant to notify the beneficial owner, shall \nnot affect the validity of the redemption of the Certificate called for redemption or any other action premised or any such notice. \n \nRedemption of portions of the Certificates by the City will re duce the outstanding principal amount  of such Certificates held b y \nDTC.  In such event, DTC may implement, through its book-entry- only system, a redemption of such Certificate held for the \naccount of DTC participants in accordance with its rules or other agreements with DTC participants and then DTC participants and \nindirect participants may implement a redemption of such Certificate from the beneficial owners.  Any such selection of Certificates \nto be redeemed will not be governed by the Ordinance and will not be conducted by the City or the Paying Agent/Registrar.  Neither \nthe City nor the Paying Agent/Registrar will have any responsibi lity to DTC participants, indirect participants or the persons for \nwhom DTC participants act as nominees, with respect to the pa yments on the Certificates or the providing of notice to DTC \nparticipants, indirect participants, or bene ficial owners of the select ion of portions of the Certificates for redemption.  See  \u201cTHE \nCERTIFICATES \u2013 Book-Entry-Only System\u201d herein. \n \nWith respect to any optional redemption of the Certificates, un less certain prerequisites to su ch redemption required by the \nOrdinance have been met and money sufficient to pay the principal of a premium, if any, and interest on the applicable Certificates \nto be redeemed will have been received by the Paying Agent/Registrar prior to the giving of such notice of redemption, such notice \nwill state that said redemption may, at the option of the City, be conditional upon the satisfaction of such prerequisites and receipt \nof such money by the Paying Agent/Registrar on or prior to th e date fixed for such redemption, or upon any prerequisite set for th \nin such notice of redemption.  If a condi tional notice of redemption is given and such  prerequisites to the redemption are not \nfulfilled, such notice will be of no force and effect, the City will not redeem such Certificates, and the Paying Agent/Registrar will \ngive notice in the manner in which the notice of redemption was given, to the effect that such Certificates have not been redeemed. \n \nDTC REDEMPTION PROVISIONS . . . The Paying Agent/Registrar and the City so  long as a book-entry-only system is used for the \nCertificates, will send any notice of redemption, notice of proposed amendment to the Ordinance or other notices with respect t o \nthe Certificates to DTC.  Any failure by DTC to advise any DTC Participant, or of any Direct Participant or Indirect Participant to \nnotify the beneficial owner, shall not affect the validity of the redemption of the Certificates called for redemption or any o ther \naction premised on any such notice.  Redemp tion of portions of the Certificates by the City will reduce the outstanding princip al \namount of such Certificates held by DTC.  In such event, DTC may implement, through its book-entry-only system, a redemption \nof such Certificates held for the account of DTC Participants in accordance with its rules or other agreements with DTC Participants \nand then Direct Participants and Indirect Participants may imple ment a redemption of such Certificates and such redemption will  \nnot be conducted by the City or the Paying/Agent Registrar.  Neither the City nor the Paying Agent/Registrar will have any \nresponsibility to DTC Participants, Indirect Participants or persons for whom DTC Participants act as nominees, with respect to the \npayments on the Certificates or the providing of notice to Direct Participants, Indirect Participants, or beneficial owners of the \nselection of portions of the Certificates for redemption. \n \nDEFEASANCE . . . General.  The Ordinance provides for the defeasance of the Certificates and the termination of the pledge of taxes \nand all other general covenants in the Ordi nance under certain circumstances.  Any Cer tificate and the interest thereon shall b e \ndeemed to be paid, retired and no longer outstanding (\u201cDefeased Certificate\u201d) within the meaning of the Ordinance, except to th e "
    },
    {
      "page_number": 9,
      "text": " 9 \nextent provided below for the Paying Agent/Registrar to continue payments and for the City to retain the right to call Defeased  \nCertificates to be paid at maturity, when the payment of all principal and interest payable with respect to such Defeased Certificates \nto the due date or dates thereof (whether such due date or dates be by reason of maturity, upon redemption, or otherwise) either (1) \nshall have been made or caused to be made in accordance with the terms thereof (including the giving of any required notice of \nredemption) or (2) shall have been provided for on or before such  due date by irrevocably depositing with or making available t o \nthe Paying Agent/Registrar or a commercial bank or trust company for such payment (a) lawful money of the United States of \nAmerica sufficient to make such payment, (b) Defeasance Securities (defined below) that mature as to principal and interest in such \namounts and at such times as will ensure the availability, without reinvestment, of sufficient money to provide for such paymen t \nand when proper arrangements have been made by the City with  the Paying Agent/Registrar for the payment of its services until \nafter all Defeased Certificates shall have become due and payable or (c) any combination of (a) and (b).  At such time as a Certificate \nshall be deemed to be a Defeased Certificate, such Certificate and the interest thereon shall no longer be secured by, payable from, \nor entitled to the benefits of, the ad valorem taxes levied and pledged as provided in the Ordinance, and such principal and interest \nshall be payable solely from such money or Defeasance Securiti es and thereafter the City will have no further responsibility wi th \nrespect to amounts available to such Paying Agent/Registrar (or other financial institution permitted by applicable law) for th e \npayment of such Defeased Certificate, including any insufficiency therein caused by the failure of the Paying Agent/Registrar ( or \nother financial institution permitted by law) to receive payment when due on the Defeased Securities. \n \nThe deposit under clause (2) above shall be deemed a payment of an Certificate when proper notice of redemption of such \nCertificates shall have been given, in accordance with the Ordinance.  Any money so deposited with the Paying Agent/Registrar or \na commercial bank or trust company may at the discretion of the City also be invested in Defeasance Securities, as hereinafter \ndefined, maturing in the amounts and at the times as set forth in the Ordinance, and all income from such Defeasance Securities  \nreceived by the Paying Agent/Registrar or a commercial bank or  trust company that is not required for the payment of the \nCertificates and interest thereon, with respect to which such money has been so deposited, shall be remitted to the City. \n \nAll money or Defeasance Securities set aside and held in trust pursuant to the provisions of the Ordinance for the payment of \nprincipal of the Certificates and premium, if any, and interest thereon, shall be applied to a nd used solely for the payment of  the \nparticular Certificates and premium, if any, and interest thereon, with respect to which such money or Defeasance Securities have \nbeen so set aside in trust.  Until all Defeased Certificates shall have become due and payable, the Paying Agent/Registrar or a  \ncommercial bank or trust company shall perform the services of Paying Agent/Registrar for such Defeased Certificates the same \nas if they had not been defeased, and the City shall make proper arrangements to provide and pay for such services as required by \nthe Ordinance. \n \nIf money or Defeasance Securities have been deposited or set aside with the Paying Agent/Registrar or a commercial bank or trust \ncompany for the payment of Certificates and such Certificates sh all not have in fact been actually paid in full, no amendment o f \nthe defeasance provisions of the Ordinance shall be made without the consent of the re gistered owner of each Certificate affected \nthereby. \n \nRetention of Rights.  To the extent that, upon the defeasance of any Defeased Certificates to be paid at its maturity, the City retains \nthe right under State law to later call any Defeased Certificates which is subject to redemption (i.e. the Certificates) in accordance \nwith the provisions of the Ordinance, th e City may call such Defeased Certifi cates for redemption upon complying with the \nprovisions of State law and upon the satisfaction of the provisions set forth above regarding such Defeased Certificates as tho ugh \nit was being defeased at the time of the exercise of the option to redeem the Defeased Certificates and the effect of the redemption \nis taken into account in determining the sufficiency of the provisions made for the payment of the Defeased Certificates. \n \nInvestments.  Any escrow agreement or other instrument entered in to between the City and the Paying Agent/Registrar or a \ncommercial bank or trust company pursuant to which money and/or Defeasance Securities are held by the Paying Agent/Registrar \nor a commercial bank or trust company for the payment of Defeased Certificates may contain provisions permitting the investment \nor reinvestment of such moneys in Defeasance Securities or the substitution of other Defeasance Securities upon the satisfaction of \ncertain requirements.  All income from such Defeasance Securities received by the Paying Agent/Registrar or a commercial bank \nor trust company which is not required for the payment of the Cert ificates and interest thereon, with respect to which such money \nhas been so deposited, will be remitted to the City. \n \nFor the purposes of these provisions, \u201cDefeasance Securities\u201d means (i) Federal Securities, (ii) noncallable obligations of an agency \nor instrumentality of the United States of  America, including obligati ons that are unconditionally guaranteed or insured by the  \nagency or instrumentality and that, on the date the City Counc il adopts or approves proceedings authorizing the issuance of \nrefunding bonds or otherwise provide for the funding of an escrow to  effect the defeasance of the Certificates are rated as to \ninvestment quality by a nationally recognized investment rating fi rm not less than \u201cAAA\u201d or it s equivalent, (iii) noncallable \nobligations of a state or an agency or a county, municipality, or  other political subdivision of a state that have been refunde d and \nthat, on the date the City Council adopts or approves proceedings authorizing the issuance of refunding bonds or otherwise provide \nfor the funding of an escrow to effect the defeasance of the Certificates, are rated as to investment quality by a nationally recognized \ninvestment rating firm no less than \u201cAAA\u201d or  its equivalent and (iv) any other then authorized securities or obligations under \napplicable state law that may be used to defease obligations such as the Certificates.  For the purposes of these provisions, \u201cFederal \nSecurities\u201d means direct, noncallable obligations of the United St ates of America, including obligations that are unconditional ly \nguaranteed by the United States of America. \n "
    },
    {
      "page_number": 10,
      "text": " 10\nThere is no assurance that the current la w will not be changed in a manner which would permit investments other than those \ndescribed above to be made with amounts deposited to defease the Certificates.  Because the Ordinance does not contractually limit \nsuch investments, registered owners may be deemed to have consented to defeasance with such other investments, notwithstanding \nthe fact that such investments may not be of the same investment quality as those currently permitted under State law.  There is no \nassurance that the ratings for U.S. Treasury securities used as Defeasance Securities or those for any other Defeasance Securit y \nwill be maintained at any particular rating category. \n \nBOOK-ENTRY-ONLY SYSTEM . . . This section describes how ownership of the Certificates is to be transferred and how the principal \nof, premium, if any, and interest on the Certificates are to be paid to and credited by DTC while the Certificates are register ed in \nits nominee\u2019s name.  The information in this section concerning DTC and the Book-Entry-Only System has been provided by DTC \nfor use in disclosure documents such as this Official Statement.   The City believes the source of such information to be reliab le, \nbut takes no responsibility for the accuracy or completeness thereof. \n \nThe City cannot and does not give any assurance that (1) DTC w ill distribute payments of debt service on the Certificates, or \nredemption or other notices, to DTC Participants, (2) DTC Participants or others will distribute debt service payments paid to DTC \nor its nominee (as the registered owner of the Certificates), or redemption or other notices, to the Beneficial Owners, or that  they \nwill do so on a timely basis, or (3) DTC will serve and act in th e manner described in this Official Statement.  The current ru les \napplicable to DTC are on file with the Securities and Exchange Commission, and the current procedures of DTC to be followed in \ndealing with DTC Participants are on file with DTC. \n \nDTC will act as securities depository for the Certificates.  The Certificates will be issued as fully-registered Certificates registered \nin the name of Cede & Co. (DTC\u2019s partnership nominee) or such other name as may be requested by an authorized representative \nof DTC. One fully-registered Certificate will be issued for each maturity of the Certificates, each in the aggregate principal amount \nof such maturity, and will be deposited with DTC.  \n \nDTC, the world\u2019s largest securities depository, is a limited-purpose trust company organized under the New York Banking Law, a \n\u201cbanking organization\u201d within the meaning of the New York Banking Law, a member of the Federal Reserve System, a \u201cclearing \ncorporation\u201d within the meaning of the New York Uniform Commerc ial Code, and a \u201cclearing agency\u201d registered pursuant to the \nprovisions of Section 17A of the Securities  Exchange Act of 1934.  DTC holds and pr ovides asset servicing for over 3.5 million \nissues of U.S. and non-U.S. equity issu es, corporate and municipal debt issues, and money market instruments (from over 100 \ncountries) that DTC\u2019s participants (\u201cDirect Participants\u201d) deposit with DTC.  DTC also facilitates the post-trade settlement among \nDirect Participants of sales and other securities transacti ons in deposited secur ities, through electroni c computerized book-en try \ntransfers and pledges between Direct Partic ipants\u2019 accounts.  This elim inates the need for physical  movement of securities \ncertificates. Direct Participants  include both U.S. and non-U.S. securities brok ers and dealers, banks, trust companies, cleari ng \ncorporations, and certain other organizations.  DTC is a wholly-owned subsidiary of The Depository Trust & Clearing Corporation \n(\u201cDTCC\u201d).  DTCC is the holding company for DTC, National Securities Clearing Corporatio n and Fixed Income Clearing \nCorporation, all of which are registered clearing agencies.  DTCC is owned by the users of its regulated subsidiaries.  Access to \nthe DTC system is also available to others such as both U.S. and non-U.S. securities brokers and dealers, banks, trust companies, \nand clearing corporations that clear through or maintain a custodial relationship with a Direct Participant, either directly or indirectly \n(\u201cIndirect Participants\u201d).  DTC has a Standard & Poor\u2019s rating of \u201cAA+.\u201d  The DTC Rules applicable to its Participants are on file \nwith the Securities and Exchange Commission.  More information about DTC can be found at www.dtcc.com. \n \nPurchases of Certificates under the DTC system must be made by or through Direct Participants, which will receive a credit for the \nCertificates on DTC\u2019s records.  The ownership interest of each actual purchaser of each Certificate (\u201cBeneficial Owner\u201d) is in turn \nto be recorded on the Direct and Indirect Participants\u2019 records. Beneficial Owners will not receive written confirmation from DTC \nof their purchase. Beneficial Owners are, however, expected to receive written confirmations providing details of the transaction, \nas well as periodic statements of their holdings, from the Direct or Indirect Participant through which the Beneficial Owner entered \ninto the transaction. Transfers of ownership interests in the Ce rtificates are to be  accomplished by entries made on the books of \nDirect and Indirect Participants acting on behalf of Beneficial Owners. Beneficial Owners will not receive certificates representing \ntheir ownership interests in Certificates, except in the event that use of the book-entry system for the Certificates is discontinued. \n \nTo facilitate subsequent transfers, all Certificates deposited by Direct Participants with DTC are registered in the name of DT C\u2019s \npartnership nominee, Cede & Co., or such ot her name as may be requested by an aut horized representative of DTC.  The deposit \nof Certificates with DTC and their registration in the name of Cede & Co. or such other DTC nominee do not effect any change in \nbeneficial ownership.  DTC has no knowledge of the actual Beneficial Owners of the Certificates; DTC\u2019s records reflect only the \nidentity of the Direct Participants to whose accounts such Certificates are credited, which may or may not be the Beneficial Owners. \nThe Direct and Indirect Participants will remain responsible fo r keeping account of their holdings on behalf of their customers . \nConveyance of notices and other co mmunications by DTC to Direct Participants, by Di rect Participants to Indirect Participants, \nand by Direct Participants and Indirect Participants to Benefi cial Owners will be governed by arrangements among them, subject \nto any statutory or regulatory requirements as may be in effect from time to time.  Beneficial Owners of Certificates may wish to \ntake certain steps to augment the transmission to them of notices  of significant events with respect to the Certificates, such as \nredemptions, tenders, defaults, and proposed amendments to the Certificate documents.   For example, Beneficial Owners of \nCertificates may wish to ascertain that the nominee holding the Certificates for their benefit has agreed to obtain and transmi t \nnotices to Beneficial Owners.  In the alternative, Beneficial Owners may wish to provide their names and addresses to the registrar \nand request that copies of notices be provided directly to them.  \n "
    },
    {
      "page_number": 11,
      "text": " 11\nRedemption notices shall be sent to DTC.  If less than all of the Certificates within a maturity are being redeemed, DTC\u2019s practice \nis to determine by lot the amount of the interest of each Direct Participant in such maturity to be redeemed.  \n \nNeither DTC nor Cede & Co. (nor any other DTC nominee) will consen t or vote with respect to Certificates unless authorized by \na Direct Participant in accordance with DTC\u2019s MMI Procedures. Under its usual procedures, DTC mails an Omnibus Proxy to the \nCity as soon as possible after the record date.  The Omnibus Proxy assigns Cede & Co.\u2019s consenting or voting rights to those Direct \nParticipants to whose accounts Certificates are credited on the record date (identified in a listing attached to the Omnibus Proxy).  \n \nAll payments on the Certificates will be made to Cede & Co., or such other nominee as may be requested by an authorized \nrepresentative of DTC.  DTC\u2019s practice is to credit Direct Pa rticipants\u2019 accounts upon DTC\u2019s receipt of funds and corresponding \ndetail information from the City or the Paying Agent/Registrar, on payable date in accordance with their respective holdings shown \non DTC\u2019s records.  Payments by Participants to Beneficial Ow ners will be governed by standing instructions and customary \npractices, as is the case with Certificates held for the accounts of customers in bearer form or registered in \u201cstreet name,\u201d and will \nbe the responsibility of such Participant and not of DTC, the Pa ying Agent/Registrar, or the City, subject to any statutory or \nregulatory requirements as may be in effe ct from time to time. Payment of redemp tion proceeds, distributions, and dividend \npayments to Cede & Co. (or such other nominee as may be requested by an authorized representative of DTC) is the responsibility \nof the City or the Paying Agent/Registrar, disbursement of such payments to Direct Participants will be the responsibility of DTC, \nand disbursement of such payments to the Beneficial Owners will be the responsibility of Direct and Indirect Participants.  \n \nDTC may discontinue providing its services as depository with respect to the Certificates at any time by giving reasonable noti ce \nto the City or the Paying Agent/Registrar.  Under such circum stances, in the event that a successor depository is not obtained,  \nCertificate certificates are required to be printed and delivered.  \n \nThe City may decide to discontinue use of the system of book-entry-only transfers through DTC (or a successor securities \ndepository).  In that event, certificates will be printed and delivered to DTC. \n \nThe information in this section concerning DTC and DTC\u2019s book-entry system has been obtained from sources that the City believes \nto be reliable, but the City does not take any responsibility for the accuracy thereof. \n \nUSE OF CERTAIN TERMS IN OTHER SECTIONS OF THIS OFFICIAL STATEMENT . . . In reading this Offici al Statement it should be \nunderstood that while the Certificates are in the book-entry-only system, references in other sections of this Official Stateme nt to \nregistered owners should be read to include the person for whic h the Participant acquires an interest in the Certificates, but (i) all \nrights of ownership must be exercised through DTC and the book-en try-only system, and (ii) except  as described above, notices \nthat are to be given to registered owners under the Ordinance will be given only to DTC. \n \nInformation concerning DTC and the Book-Entry-Only System has been obtained from DTC and is not guaranteed as to accuracy \nor completeness by, and is not to be construed as a representation by the City, the Financial Advisor, or the Purchaser. \n \nP\nAYING AGENT/REGISTRAR . . . The initial Paying Agent/Registrar is The Bank of New York Mellon Trust Company, National \nAssociation, Houston, Texas.  In the Ordinance, the City retains the right to replace the Paying Agent/Registrar.  The City covenants \nto maintain and provide a Paying Agent/Registrar at all times until the Certificates are duly paid and any successor Paying \nAgent/Registrar shall be a commercial bank or trust company orga nized under the laws of the Stat e of Texas or other entity duly  \nqualified and legally authorized to serve as and perform the dutie s and services of Paying Agent/Registrar for the Certificates .  \nUpon any change in the Paying Agent/Registrar  for the Certificates, the City agrees to  promptly cause a written notice thereof to \nbe sent to each registered owner of the Certificates by United States mail, first-class, postage prepaid, which notice shall also give \nthe address of the new Paying Agent/Registrar. \n \nTRANSFER, EXCHANGE AND REGISTRATION . . . If the Book-Entry-Only System should be  discontinued, the Certificates may be \ntransferred and exchanged on the registration books of the Payi ng Agent/Registrar only upon presentation and surrender to the \nPaying Agent/Registrar and such transfer or exchange shall be w ithout expense or service charge to the registered owner, except  \nfor any tax or other governmental charges required to be paid with respect to such registration, exchange and transfer.  \n \nCertificates may be assigned by the execution of an assignment form on the Certificates or by other instrument of transfer and \nassignment acceptable to the Paying Agent/Registrar.  New Certificates will be delivered by the Paying Agent/Registrar, in lieu of \nthe Certificates being transferred or exchanged, at the design ated office of the Paying Agent/Reg istrar, or sent by United Stat es \nmail, first class, postage prepaid, to the new registered owner or his designee.  To the extent possible, new Certificates issued in an \nexchange or transfer of Certificates will be delivered to the re gistered owner or assignee of the registered owner in not more than \nthree business days after the receipt of the Certificates to be canceled, and the written instrument of transfer or request for exchange \nduly executed by the registered owner or his duly authorized ag ent, in form satisfactory to the Paying Agent/Registrar.  New \nCertificates registered and delivered in an exchange or transfer shall be in any integral multiple of $5,000 for any one maturity and \nfor a like aggregate principal amount as the Certificates surrendered for exchange or transfer.  See \u201cBOOK-ENTRY-ONLY SYSTEM\u201d \nherein for a description of the system to be utilized initially in regard to ownership and transferability of the Certificates.  Neither \nthe City nor the Paying Agent/Registrar shall be required to transfer or exchange any Certificate called for redemption, in whole or \nin part, within 45 days of the date fixed for redemption; provided, however, such limitation of transfer shall not be applicable to an \nexchange by the registered owner of the uncalled balance of a Certificate. \n "
    },
    {
      "page_number": 12,
      "text": " 12\nRECORD DATE FOR INTEREST PAYMENT . . . The record date (\u201cRecord Date\u201d) for the interest payable on the Certificates on any \ninterest payment date means the close of business on the last business day of the preceding month.  In the event of a non-payment \nof interest on a scheduled payment date, and for 30 days thereafter, a new record date for such interest payment (a \u201cSpecial Record \nDate\u201d) will be established by the Paying Agent/Registrar, if and wh en funds for the payment of such interest have been received  \nfrom the City.  Notice of the Special Record Date and of the scheduled payment date of the past due interest (\u201cSpecial Payment \nDate,\u201d which shall be 15 days after the Special Record Date) shal l be sent at least five busine ss days prior to the Special Rec ord \nDate by United States mail, first-class postage prepaid, to the address of each owner of a Certificate appearing on the registr ation \nbooks of the Paying Agent/Registrar at the close of business on th e last business day next preceding the date of mailing of suc h \nnotice. \n \nCERTIFICATEHOLDERS\u2019 REMEDIES . . . The Ordinance establishes specific events of default with respect to the Certificates.  If the \nCity defaults in the payment of the principal of or interest on  the Certificates when due, or the City defaults in the observan ce or \nperformance of any of the covenants, conditions, or obligations of  the City, the failure to perform which materially, adversely  \naffects the rights of the owners, including but not limited to, their prospect or ability to be repaid in accordance with the Ordinance, \nand the continuation thereof for a period of 60 days after notice of such default is given by any owner to the City, the Ordina nce \nprovides that any registered owner is entitled to seek a writ  of mandamus from a court of proper jurisdiction requiring the Cit y to \nmake such payment or observe and perform such covenants, obligations, or conditions.  \n \nThe issuance of a writ of mandamus may be  sought if there is no other available reme dy at law to compel performance of the \nCertificates or the Ordinance and the City\u2019s  obligations are not uncertain or disputed. The remedy of mandamus is controlled by  \nequitable principles, so rests with the discretion of the court, but may not be arbitrarily refused. There is no acceleration of maturity \nof the Certificates in the event of defaul t and, consequently, the remedy of mandamus may have to be relied upon from year to \nyear.  \n \nThe Ordinance does not provide for the appointment of a trustee to represent the interest of the Certificateholders upon any failure \nof the City to perform in accordance with the terms of the Ordinance, or upon any other condition and accordingly all legal actions \nto enforce such remedies would have to be undertaken at the initiative of, and be financed by, the registered owners.  \n \nOn June 30, 2006, the Texas Supreme Court ruled in Tooke v. City of Mexia, 49 Tex. Sup. Ct. J. 819 (Tex. 2006), that a waiver of \ngovernmental immunity in a contractual dispute must be provided for by statute in \u201cclear and unambiguous\u201d language.  Because it \nis unclear whether the Texas legislature has effectively waived the City\u2019s governmental immunity from a suit for money damages, \nCertificateholders may not be able to bring such a suit against the City for breach of the Certificates or covenants in the Ordinance. \nEven if a judgment against the City could be obtained, it could not be enforced by di rect levy and execution against the City\u2019s  \nproperty. Further, the registered owners cannot themselves foreclose on property within the City or sell property within the City to \nenforce the tax lien on taxable property to pay the principal of and interest on the Certificates.  \n \nOn April 1, 2016, the Texas Supreme Court ruled in Wasson Interests, Ltd. v. City of Jacksonville, 59 Tex. Sup. Ct. J. 524 (Tex. \n2016) that governmental immunity does not imbue a city with deri vative immunity when it performs proprietary, as opposed to \ngovernmental, functions in respect to contracts executed by a city.  Texas jurisprudence has generally held that proprietary functions \nare those conducted by a city in its privat e capacity, for the benefit only of those within its corporate limits, and not as an  arm of \nthe government or under the authority or for the benefit of the state.  In its decision, the Court held that since the Local Government \nImmunity Waiver Act waives governmental immunity in certain breach of contract claims without addressing whether the waiver \napplies to a governmental function or a propr ietary function of a city, the Court coul d not reasonably read the Local Governmen t \nImmunity Waiver Act to evidence legislative intent to waive immunity when a city performs a proprietary function. \n \nAs noted above, the Ordinance provides that holders of Certif icates may exercise the remedy of mandamus to enforce the \nobligations of the City under the Ordinance.  Neither the remedy of mandamus nor any other type of injunctive relief was at iss\nue \nin Tooke, and it is unclear whether Tooke will be construed to have any effect with respect to the exercise of mandamus, as such \nremedy has been interpreted by Texas courts. In general, Texas courts have held that a writ of mandamus may be issued to require \npublic officials to perform ministerial acts that clearly pertain to their duties. Texas courts have held that a ministerial act is defined \nas a legal duty that is prescribed and defined with a precision and certainty that leaves nothing to the exercise of discretion  or \njudgment, though mandamus is not available to enforce purely contractual duties. However, mandamus may be used to require a \npublic officer to perform legally imposed ministerial duties necessary for the performance of a valid contract to which the State or \na political subdivision of the State is a party (including the payment of monies due under a contract). \n \nFurthermore, the City is eligible to seek  relief from its creditors under Chapter 9 of the U.S. Bankruptcy Code (\u201cChapter 9\u201d). \nAlthough Chapter 9 provides for the recognition of a security interest represented by a specifically pledged source of revenues, the \npledge of ad valorem taxes in support of a general obligation of a bankrupt entity is not specifically recognized as a security interest \nunder Chapter 9.  Chapter 9 also includes an automatic stay provision that would prohibit, without Bankruptcy Court approval, the \nprosecution of any other legal action by creditors or Certificateh olders of an entity which has sought protection under Chapter  9. \nTherefore, should the City avail itself of Chapter 9 protection from creditors, the ability to enforce would be subject to the approval \nof the Bankruptcy Court (which could require that the action be heard in Bankruptcy Court instead of other federal or state court); \nand the Bankruptcy Code provides for broad discretionary powers of a Bankruptcy Court in administering any proceeding brought \nbefore it.  The opinion of Bond Counsel will  note that all opinions relative to the enforceability of the Certificates are qual ified \nwith respect to governmental immunity and the customary rights of debtors relative to  their creditors and general principles of  \nequity which permit the exercise of judicial discretion. "
    }
  ],
  "notes": [
    "Delivery date not found in selected pages."
  ]
}